numtmath/__init__.py
numtmath/numtmath.py
numtmath-1.6.0.1.dist-info/LICENSE
numtmath-1.6.0.1.dist-info/METADATA
numtmath-1.6.0.1.dist-info/WHEEL
numtmath-1.6.0.1.dist-info/top_level.txt
numtmath-1.6.0.1.dist-info/RECORD
